MechElastic-1.2.29.data/data/LICENSE.txt
MechElastic-1.2.29.data/scripts/MechElastic.py
mechelastic/__init__.py
mechelastic/calculate_elastic.py
mechelastic/calculate_elastic_anisotropy.py
mechelastic/from_mp.py
mechelastic/version.py
mechelastic/comms/__init__.py
mechelastic/comms/printer.py
mechelastic/core/__init__.py
mechelastic/core/brillouin_zone.py
mechelastic/core/elastic_properties.py
mechelastic/core/elastic_properties_2d.py
mechelastic/core/elate.py
mechelastic/core/isosurface.py
mechelastic/core/structure.py
mechelastic/core/surface.py
mechelastic/eos/__init__.py
mechelastic/eos/eos.py
mechelastic/parsers/__init__.py
mechelastic/parsers/abinitparser.py
mechelastic/parsers/qe_ElaStic_parser.py
mechelastic/parsers/qe_thermo_pw_parser.py
mechelastic/parsers/vaspparser.py
mechelastic/tests/__init__.py
mechelastic/tests/ductile.py
mechelastic/tests/eigenvals.py
mechelastic/tests/stability.py
mechelastic/tests/symmetry.py
mechelastic/utils/__init__.py
mechelastic/utils/constants.py
mechelastic/utils/crystalutils.py
mechelastic/utils/elements.py
MechElastic-1.2.29.dist-info/LICENSE.txt
MechElastic-1.2.29.dist-info/METADATA
MechElastic-1.2.29.dist-info/WHEEL
MechElastic-1.2.29.dist-info/top_level.txt
MechElastic-1.2.29.dist-info/RECORD
